{
    "schemes": [
        "http"
    ],
    "swagger": "2.0",
    "info": {
        "description": "quebec core 模块后端",
        "title": "quebec core Swagger API接口文档",
        "contact": {
            "name": "Lyon Mu",
            "url": "https://github.com/lyonmu",
            "email": "lyonmu@foxmail.com"
        },
        "license": {
            "name": "MIT",
            "url": "https://github.com/lyonmu/quebec/blob/master/LICENSE"
        },
        "version": "v0.0.1"
    },
    "host": "http://localhost:59024",
    "basePath": "/core/api",
    "paths": {
        "/v1/system/captcha": {
            "get": {
                "description": "获取验证码,返回包括随机数id,base64,验证码长度",
                "produces": [
                    "application/json"
                ],
                "tags": [
                    "系统管理"
                ],
                "summary": "获取验证码",
                "responses": {
                    "200": {
                        "description": "50000,success",
                        "schema": {
                            "allOf": [
                                {
                                    "$ref": "#/definitions/code.Response"
                                },
                                {
                                    "type": "object",
                                    "properties": {
                                        "code": {
                                            "type": "number"
                                        },
                                        "data": {
                                            "$ref": "#/definitions/response.CaptchaResponse"
                                        },
                                        "message": {
                                            "type": "string"
                                        }
                                    }
                                }
                            ]
                        }
                    }
                }
            }
        },
        "/v1/system/login": {
            "post": {
                "description": "使用用户名密码登陆系统",
                "produces": [
                    "application/json"
                ],
                "tags": [
                    "系统管理"
                ],
                "summary": "登陆",
                "parameters": [
                    {
                        "description": "用户登陆信息",
                        "name": "data",
                        "in": "body",
                        "required": true,
                        "schema": {
                            "$ref": "#/definitions/request.SystemLoginRequest"
                        }
                    }
                ],
                "responses": {
                    "200": {
                        "description": "50000,success",
                        "schema": {
                            "allOf": [
                                {
                                    "$ref": "#/definitions/code.Response"
                                },
                                {
                                    "type": "object",
                                    "properties": {
                                        "code": {
                                            "type": "number"
                                        },
                                        "data": {
                                            "$ref": "#/definitions/response.SystemInfoResponse"
                                        },
                                        "message": {
                                            "type": "string"
                                        }
                                    }
                                }
                            ]
                        }
                    }
                }
            }
        },
        "/v1/system/logout": {
            "get": {
                "description": "退出登陆系统",
                "produces": [
                    "application/json"
                ],
                "tags": [
                    "系统管理"
                ],
                "summary": "退出登陆",
                "responses": {
                    "200": {
                        "description": "50000,success",
                        "schema": {
                            "allOf": [
                                {
                                    "$ref": "#/definitions/code.Response"
                                },
                                {
                                    "type": "object",
                                    "properties": {
                                        "code": {
                                            "type": "number"
                                        },
                                        "message": {
                                            "type": "string"
                                        }
                                    }
                                }
                            ]
                        }
                    }
                }
            }
        },
        "/v1/system/onlineuser/clearance/{id}": {
            "delete": {
                "description": "清除在线用户",
                "produces": [
                    "application/json"
                ],
                "tags": [
                    "系统管理"
                ],
                "summary": "清除在线用户",
                "parameters": [
                    {
                        "type": "string",
                        "description": "ID",
                        "name": "id",
                        "in": "path",
                        "required": true
                    }
                ],
                "responses": {
                    "200": {
                        "description": "50000,success",
                        "schema": {
                            "allOf": [
                                {
                                    "$ref": "#/definitions/code.Response"
                                },
                                {
                                    "type": "object",
                                    "properties": {
                                        "code": {
                                            "type": "number"
                                        },
                                        "message": {
                                            "type": "string"
                                        }
                                    }
                                }
                            ]
                        }
                    }
                }
            }
        },
        "/v1/system/onlineuser/label": {
            "get": {
                "description": "获取在线用户标签",
                "produces": [
                    "application/json"
                ],
                "tags": [
                    "系统管理"
                ],
                "summary": "在线用户标签",
                "responses": {
                    "200": {
                        "description": "50000,success",
                        "schema": {
                            "allOf": [
                                {
                                    "$ref": "#/definitions/code.Response"
                                },
                                {
                                    "type": "object",
                                    "properties": {
                                        "code": {
                                            "type": "number"
                                        },
                                        "data": {
                                            "type": "array",
                                            "items": {
                                                "$ref": "#/definitions/response.Options"
                                            }
                                        },
                                        "message": {
                                            "type": "string"
                                        }
                                    }
                                }
                            ]
                        }
                    }
                }
            }
        },
        "/v1/system/onlineuser/list": {
            "get": {
                "description": "获取在线用户列表",
                "produces": [
                    "application/json"
                ],
                "tags": [
                    "系统管理"
                ],
                "summary": "在线用户列表",
                "parameters": [
                    {
                        "type": "string",
                        "description": "访问IP",
                        "name": "access_ip",
                        "in": "query"
                    },
                    {
                        "type": "integer",
                        "description": "结束时间",
                        "name": "end_time",
                        "in": "query"
                    },
                    {
                        "minimum": 1,
                        "type": "integer",
                        "default": 1,
                        "description": "页码",
                        "name": "page",
                        "in": "query",
                        "required": true
                    },
                    {
                        "maximum": 1000,
                        "minimum": 10,
                        "type": "integer",
                        "default": 10,
                        "description": "每页条数",
                        "name": "page_size",
                        "in": "query",
                        "required": true
                    },
                    {
                        "type": "integer",
                        "description": "开始时间",
                        "name": "start_time",
                        "in": "query"
                    },
                    {
                        "type": "string",
                        "description": "用户ID",
                        "name": "user_id",
                        "in": "query"
                    }
                ],
                "responses": {
                    "200": {
                        "description": "50000,success",
                        "schema": {
                            "allOf": [
                                {
                                    "$ref": "#/definitions/code.Response"
                                },
                                {
                                    "type": "object",
                                    "properties": {
                                        "code": {
                                            "type": "number"
                                        },
                                        "data": {
                                            "$ref": "#/definitions/response.SystemOnlineUserListResp"
                                        },
                                        "message": {
                                            "type": "string"
                                        }
                                    }
                                }
                            ]
                        }
                    }
                }
            }
        },
        "/v1/system/role": {
            "post": {
                "description": "添加角色信息",
                "produces": [
                    "application/json"
                ],
                "tags": [
                    "系统管理"
                ],
                "summary": "添加角色信息",
                "parameters": [
                    {
                        "description": "角色信息",
                        "name": "data",
                        "in": "body",
                        "required": true,
                        "schema": {
                            "$ref": "#/definitions/request.SystemRoleAddReq"
                        }
                    }
                ],
                "responses": {
                    "200": {
                        "description": "50000,success",
                        "schema": {
                            "allOf": [
                                {
                                    "$ref": "#/definitions/code.Response"
                                },
                                {
                                    "type": "object",
                                    "properties": {
                                        "code": {
                                            "type": "number"
                                        },
                                        "message": {
                                            "type": "string"
                                        }
                                    }
                                }
                            ]
                        }
                    }
                }
            }
        },
        "/v1/system/role/enable/{id}": {
            "put": {
                "description": "启停角色状态",
                "produces": [
                    "application/json"
                ],
                "tags": [
                    "系统管理"
                ],
                "summary": "启停角色",
                "parameters": [
                    {
                        "type": "string",
                        "description": "ID",
                        "name": "id",
                        "in": "path",
                        "required": true
                    },
                    {
                        "description": "状态 [1: 启用, 2: 禁用]",
                        "name": "data",
                        "in": "body",
                        "required": true,
                        "schema": {
                            "$ref": "#/definitions/request.EnableReq"
                        }
                    }
                ],
                "responses": {
                    "200": {
                        "description": "50000,success",
                        "schema": {
                            "allOf": [
                                {
                                    "$ref": "#/definitions/code.Response"
                                },
                                {
                                    "type": "object",
                                    "properties": {
                                        "code": {
                                            "type": "number"
                                        },
                                        "message": {
                                            "type": "string"
                                        }
                                    }
                                }
                            ]
                        }
                    }
                }
            }
        },
        "/v1/system/role/label": {
            "get": {
                "description": "获取角色标签",
                "produces": [
                    "application/json"
                ],
                "tags": [
                    "系统管理"
                ],
                "summary": "角色标签",
                "responses": {
                    "200": {
                        "description": "50000,success",
                        "schema": {
                            "allOf": [
                                {
                                    "$ref": "#/definitions/code.Response"
                                },
                                {
                                    "type": "object",
                                    "properties": {
                                        "code": {
                                            "type": "number"
                                        },
                                        "data": {
                                            "type": "array",
                                            "items": {
                                                "$ref": "#/definitions/response.Options"
                                            }
                                        },
                                        "message": {
                                            "type": "string"
                                        }
                                    }
                                }
                            ]
                        }
                    }
                }
            }
        },
        "/v1/system/role/list": {
            "get": {
                "description": "获取全部角色列表",
                "produces": [
                    "application/json"
                ],
                "tags": [
                    "系统管理"
                ],
                "summary": "全部角色列表",
                "parameters": [
                    {
                        "type": "string",
                        "description": "角色名称",
                        "name": "name",
                        "in": "query"
                    },
                    {
                        "enum": [
                            1,
                            2
                        ],
                        "type": "integer",
                        "format": "int32",
                        "x-enum-varnames": [
                            "Yes",
                            "No"
                        ],
                        "description": "角色状态 [1: 启用, 2: 禁用]",
                        "name": "status",
                        "in": "query"
                    }
                ],
                "responses": {
                    "200": {
                        "description": "50000,success",
                        "schema": {
                            "allOf": [
                                {
                                    "$ref": "#/definitions/code.Response"
                                },
                                {
                                    "type": "object",
                                    "properties": {
                                        "code": {
                                            "type": "number"
                                        },
                                        "data": {
                                            "$ref": "#/definitions/response.SystemRoleListResp"
                                        },
                                        "message": {
                                            "type": "string"
                                        }
                                    }
                                }
                            ]
                        }
                    }
                }
            }
        },
        "/v1/system/role/page": {
            "get": {
                "description": "获取角色分页列表",
                "produces": [
                    "application/json"
                ],
                "tags": [
                    "系统管理"
                ],
                "summary": "角色分页列表",
                "parameters": [
                    {
                        "type": "string",
                        "description": "角色名称",
                        "name": "name",
                        "in": "query"
                    },
                    {
                        "minimum": 1,
                        "type": "integer",
                        "default": 1,
                        "description": "页码",
                        "name": "page",
                        "in": "query",
                        "required": true
                    },
                    {
                        "maximum": 1000,
                        "minimum": 10,
                        "type": "integer",
                        "default": 10,
                        "description": "每页条数",
                        "name": "page_size",
                        "in": "query",
                        "required": true
                    },
                    {
                        "enum": [
                            1,
                            2
                        ],
                        "type": "integer",
                        "format": "int32",
                        "x-enum-varnames": [
                            "Yes",
                            "No"
                        ],
                        "description": "角色状态 [1: 启用, 2: 禁用]",
                        "name": "status",
                        "in": "query"
                    }
                ],
                "responses": {
                    "200": {
                        "description": "50000,success",
                        "schema": {
                            "allOf": [
                                {
                                    "$ref": "#/definitions/code.Response"
                                },
                                {
                                    "type": "object",
                                    "properties": {
                                        "code": {
                                            "type": "number"
                                        },
                                        "data": {
                                            "$ref": "#/definitions/response.SystemRoleListResp"
                                        },
                                        "message": {
                                            "type": "string"
                                        }
                                    }
                                }
                            ]
                        }
                    }
                }
            }
        },
        "/v1/system/role/{id}": {
            "get": {
                "description": "获取角色详情",
                "produces": [
                    "application/json"
                ],
                "tags": [
                    "系统管理"
                ],
                "summary": "获取角色详情",
                "parameters": [
                    {
                        "type": "string",
                        "description": "ID",
                        "name": "id",
                        "in": "path",
                        "required": true
                    }
                ],
                "responses": {
                    "200": {
                        "description": "50000,success",
                        "schema": {
                            "allOf": [
                                {
                                    "$ref": "#/definitions/code.Response"
                                },
                                {
                                    "type": "object",
                                    "properties": {
                                        "code": {
                                            "type": "number"
                                        },
                                        "data": {
                                            "$ref": "#/definitions/response.SystemRoleResp"
                                        },
                                        "message": {
                                            "type": "string"
                                        }
                                    }
                                }
                            ]
                        }
                    }
                }
            },
            "put": {
                "description": "编辑角色信息",
                "produces": [
                    "application/json"
                ],
                "tags": [
                    "系统管理"
                ],
                "summary": "编辑角色信息",
                "parameters": [
                    {
                        "type": "string",
                        "description": "ID",
                        "name": "id",
                        "in": "path",
                        "required": true
                    },
                    {
                        "description": "角色信息",
                        "name": "data",
                        "in": "body",
                        "required": true,
                        "schema": {
                            "$ref": "#/definitions/request.SystemRoleAddReq"
                        }
                    }
                ],
                "responses": {
                    "200": {
                        "description": "50000,success",
                        "schema": {
                            "allOf": [
                                {
                                    "$ref": "#/definitions/code.Response"
                                },
                                {
                                    "type": "object",
                                    "properties": {
                                        "code": {
                                            "type": "number"
                                        },
                                        "message": {
                                            "type": "string"
                                        }
                                    }
                                }
                            ]
                        }
                    }
                }
            },
            "delete": {
                "description": "删除角色",
                "produces": [
                    "application/json"
                ],
                "tags": [
                    "系统管理"
                ],
                "summary": "删除角色",
                "parameters": [
                    {
                        "type": "string",
                        "description": "ID",
                        "name": "id",
                        "in": "path",
                        "required": true
                    }
                ],
                "responses": {
                    "200": {
                        "description": "50000,success",
                        "schema": {
                            "allOf": [
                                {
                                    "$ref": "#/definitions/code.Response"
                                },
                                {
                                    "type": "object",
                                    "properties": {
                                        "code": {
                                            "type": "number"
                                        },
                                        "message": {
                                            "type": "string"
                                        }
                                    }
                                }
                            ]
                        }
                    }
                }
            }
        },
        "/v1/system/user": {
            "post": {
                "description": "添加用户信息",
                "produces": [
                    "application/json"
                ],
                "tags": [
                    "系统管理"
                ],
                "summary": "添加用户信息",
                "parameters": [
                    {
                        "description": "用户信息",
                        "name": "data",
                        "in": "body",
                        "required": true,
                        "schema": {
                            "$ref": "#/definitions/request.SystemUserAddReq"
                        }
                    }
                ],
                "responses": {
                    "200": {
                        "description": "50000,success",
                        "schema": {
                            "allOf": [
                                {
                                    "$ref": "#/definitions/code.Response"
                                },
                                {
                                    "type": "object",
                                    "properties": {
                                        "code": {
                                            "type": "number"
                                        },
                                        "message": {
                                            "type": "string"
                                        }
                                    }
                                }
                            ]
                        }
                    }
                }
            }
        },
        "/v1/system/user/enable/{id}": {
            "put": {
                "description": "启停用户状态",
                "produces": [
                    "application/json"
                ],
                "tags": [
                    "系统管理"
                ],
                "summary": "启停用户",
                "parameters": [
                    {
                        "type": "string",
                        "description": "ID",
                        "name": "id",
                        "in": "path",
                        "required": true
                    },
                    {
                        "description": "状态 [1: 启用, 2: 禁用]",
                        "name": "data",
                        "in": "body",
                        "required": true,
                        "schema": {
                            "$ref": "#/definitions/request.EnableReq"
                        }
                    }
                ],
                "responses": {
                    "200": {
                        "description": "50000,success",
                        "schema": {
                            "allOf": [
                                {
                                    "$ref": "#/definitions/code.Response"
                                },
                                {
                                    "type": "object",
                                    "properties": {
                                        "code": {
                                            "type": "number"
                                        },
                                        "message": {
                                            "type": "string"
                                        }
                                    }
                                }
                            ]
                        }
                    }
                }
            }
        },
        "/v1/system/user/label": {
            "get": {
                "description": "获取用户标签",
                "produces": [
                    "application/json"
                ],
                "tags": [
                    "系统管理"
                ],
                "summary": "用户标签",
                "responses": {
                    "200": {
                        "description": "50000,success",
                        "schema": {
                            "allOf": [
                                {
                                    "$ref": "#/definitions/code.Response"
                                },
                                {
                                    "type": "object",
                                    "properties": {
                                        "code": {
                                            "type": "number"
                                        },
                                        "data": {
                                            "type": "array",
                                            "items": {
                                                "$ref": "#/definitions/response.Options"
                                            }
                                        },
                                        "message": {
                                            "type": "string"
                                        }
                                    }
                                }
                            ]
                        }
                    }
                }
            }
        },
        "/v1/system/user/list": {
            "get": {
                "description": "获取全部用户列表",
                "produces": [
                    "application/json"
                ],
                "tags": [
                    "系统管理"
                ],
                "summary": "全部用户列表",
                "parameters": [
                    {
                        "type": "string",
                        "description": "用户邮箱",
                        "name": "email",
                        "in": "query"
                    },
                    {
                        "type": "string",
                        "description": "用户昵称",
                        "name": "nickname",
                        "in": "query"
                    },
                    {
                        "type": "string",
                        "description": "角色ID",
                        "name": "role_id",
                        "in": "query"
                    },
                    {
                        "enum": [
                            1,
                            2
                        ],
                        "type": "integer",
                        "format": "int32",
                        "x-enum-varnames": [
                            "Yes",
                            "No"
                        ],
                        "description": "用户状态 [1: 启用, 2: 禁用]",
                        "name": "status",
                        "in": "query"
                    },
                    {
                        "type": "string",
                        "description": "用户名",
                        "name": "username",
                        "in": "query"
                    }
                ],
                "responses": {
                    "200": {
                        "description": "50000,success",
                        "schema": {
                            "allOf": [
                                {
                                    "$ref": "#/definitions/code.Response"
                                },
                                {
                                    "type": "object",
                                    "properties": {
                                        "code": {
                                            "type": "number"
                                        },
                                        "data": {
                                            "$ref": "#/definitions/response.SystemUserListResp"
                                        },
                                        "message": {
                                            "type": "string"
                                        }
                                    }
                                }
                            ]
                        }
                    }
                }
            }
        },
        "/v1/system/user/page": {
            "get": {
                "description": "获取用户分页列表",
                "produces": [
                    "application/json"
                ],
                "tags": [
                    "系统管理"
                ],
                "summary": "用户分页列表",
                "parameters": [
                    {
                        "type": "string",
                        "description": "用户邮箱",
                        "name": "email",
                        "in": "query"
                    },
                    {
                        "type": "string",
                        "description": "用户昵称",
                        "name": "nickname",
                        "in": "query"
                    },
                    {
                        "minimum": 1,
                        "type": "integer",
                        "default": 1,
                        "description": "页码",
                        "name": "page",
                        "in": "query",
                        "required": true
                    },
                    {
                        "maximum": 1000,
                        "minimum": 10,
                        "type": "integer",
                        "default": 10,
                        "description": "每页条数",
                        "name": "page_size",
                        "in": "query",
                        "required": true
                    },
                    {
                        "type": "string",
                        "description": "角色ID",
                        "name": "role_id",
                        "in": "query"
                    },
                    {
                        "enum": [
                            1,
                            2
                        ],
                        "type": "integer",
                        "format": "int32",
                        "x-enum-varnames": [
                            "Yes",
                            "No"
                        ],
                        "description": "用户状态 [1: 启用, 2: 禁用]",
                        "name": "status",
                        "in": "query"
                    },
                    {
                        "type": "string",
                        "description": "用户名名称",
                        "name": "username",
                        "in": "query"
                    }
                ],
                "responses": {
                    "200": {
                        "description": "50000,success",
                        "schema": {
                            "allOf": [
                                {
                                    "$ref": "#/definitions/code.Response"
                                },
                                {
                                    "type": "object",
                                    "properties": {
                                        "code": {
                                            "type": "number"
                                        },
                                        "data": {
                                            "$ref": "#/definitions/response.SystemUserListResp"
                                        },
                                        "message": {
                                            "type": "string"
                                        }
                                    }
                                }
                            ]
                        }
                    }
                }
            }
        },
        "/v1/system/user/password/self": {
            "put": {
                "description": "修改自己的密码",
                "produces": [
                    "application/json"
                ],
                "tags": [
                    "系统管理"
                ],
                "summary": "修改自己的密码",
                "parameters": [
                    {
                        "description": "用户密码信息",
                        "name": "data",
                        "in": "body",
                        "required": true,
                        "schema": {
                            "$ref": "#/definitions/request.SystemUserEditPasswordReq"
                        }
                    }
                ],
                "responses": {
                    "200": {
                        "description": "50000,success",
                        "schema": {
                            "allOf": [
                                {
                                    "$ref": "#/definitions/code.Response"
                                },
                                {
                                    "type": "object",
                                    "properties": {
                                        "code": {
                                            "type": "number"
                                        },
                                        "message": {
                                            "type": "string"
                                        }
                                    }
                                }
                            ]
                        }
                    }
                }
            }
        },
        "/v1/system/user/password/{id}": {
            "put": {
                "description": "修改用户密码",
                "produces": [
                    "application/json"
                ],
                "tags": [
                    "系统管理"
                ],
                "summary": "修改用户密码",
                "parameters": [
                    {
                        "type": "string",
                        "description": "ID",
                        "name": "id",
                        "in": "path",
                        "required": true
                    },
                    {
                        "description": "用户密码信息",
                        "name": "data",
                        "in": "body",
                        "required": true,
                        "schema": {
                            "$ref": "#/definitions/request.SystemUserEditPasswordReq"
                        }
                    }
                ],
                "responses": {
                    "200": {
                        "description": "50000,success",
                        "schema": {
                            "allOf": [
                                {
                                    "$ref": "#/definitions/code.Response"
                                },
                                {
                                    "type": "object",
                                    "properties": {
                                        "code": {
                                            "type": "number"
                                        },
                                        "message": {
                                            "type": "string"
                                        }
                                    }
                                }
                            ]
                        }
                    }
                }
            }
        },
        "/v1/system/user/{id}": {
            "get": {
                "description": "获取用户详情",
                "produces": [
                    "application/json"
                ],
                "tags": [
                    "系统管理"
                ],
                "summary": "获取用户详情",
                "parameters": [
                    {
                        "type": "string",
                        "description": "ID",
                        "name": "id",
                        "in": "path",
                        "required": true
                    }
                ],
                "responses": {
                    "200": {
                        "description": "50000,success",
                        "schema": {
                            "allOf": [
                                {
                                    "$ref": "#/definitions/code.Response"
                                },
                                {
                                    "type": "object",
                                    "properties": {
                                        "code": {
                                            "type": "number"
                                        },
                                        "data": {
                                            "$ref": "#/definitions/response.SystemUserResp"
                                        },
                                        "message": {
                                            "type": "string"
                                        }
                                    }
                                }
                            ]
                        }
                    }
                }
            },
            "put": {
                "description": "编辑用户信息",
                "produces": [
                    "application/json"
                ],
                "tags": [
                    "系统管理"
                ],
                "summary": "编辑用户信息",
                "parameters": [
                    {
                        "type": "string",
                        "description": "ID",
                        "name": "id",
                        "in": "path",
                        "required": true
                    },
                    {
                        "description": "用户信息",
                        "name": "data",
                        "in": "body",
                        "required": true,
                        "schema": {
                            "$ref": "#/definitions/request.SystemUserUpdateReq"
                        }
                    }
                ],
                "responses": {
                    "200": {
                        "description": "50000,success",
                        "schema": {
                            "allOf": [
                                {
                                    "$ref": "#/definitions/code.Response"
                                },
                                {
                                    "type": "object",
                                    "properties": {
                                        "code": {
                                            "type": "number"
                                        },
                                        "message": {
                                            "type": "string"
                                        }
                                    }
                                }
                            ]
                        }
                    }
                }
            },
            "delete": {
                "description": "删除用户",
                "produces": [
                    "application/json"
                ],
                "tags": [
                    "系统管理"
                ],
                "summary": "删除用户",
                "parameters": [
                    {
                        "type": "string",
                        "description": "ID",
                        "name": "id",
                        "in": "path",
                        "required": true
                    }
                ],
                "responses": {
                    "200": {
                        "description": "50000,success",
                        "schema": {
                            "allOf": [
                                {
                                    "$ref": "#/definitions/code.Response"
                                },
                                {
                                    "type": "object",
                                    "properties": {
                                        "code": {
                                            "type": "number"
                                        },
                                        "message": {
                                            "type": "string"
                                        }
                                    }
                                }
                            ]
                        }
                    }
                }
            }
        }
    },
    "definitions": {
        "code.Response": {
            "type": "object",
            "properties": {
                "code": {
                    "type": "integer",
                    "example": 50000
                },
                "data": {},
                "message": {
                    "type": "string",
                    "example": "success"
                }
            }
        },
        "common.OperationType": {
            "type": "integer",
            "enum": [
                1
            ],
            "x-enum-varnames": [
                "OperationLogin"
            ]
        },
        "constant.YesOrNo": {
            "type": "integer",
            "format": "int32",
            "enum": [
                1,
                2
            ],
            "x-enum-varnames": [
                "Yes",
                "No"
            ]
        },
        "request.EnableReq": {
            "type": "object",
            "required": [
                "status"
            ],
            "properties": {
                "status": {
                    "description": "状态 [1: 启用, 2: 禁用]",
                    "maximum": 2,
                    "minimum": 1,
                    "allOf": [
                        {
                            "$ref": "#/definitions/constant.YesOrNo"
                        }
                    ]
                }
            }
        },
        "request.SystemLoginRequest": {
            "type": "object",
            "required": [
                "captcha",
                "captcha_id",
                "password",
                "username"
            ],
            "properties": {
                "captcha": {
                    "description": "验证码",
                    "type": "string"
                },
                "captcha_id": {
                    "description": "验证码id",
                    "type": "string"
                },
                "password": {
                    "description": "密码",
                    "type": "string"
                },
                "username": {
                    "description": "用户名",
                    "type": "string"
                }
            }
        },
        "request.SystemRoleAddReq": {
            "type": "object",
            "required": [
                "name"
            ],
            "properties": {
                "name": {
                    "description": "角色名称",
                    "type": "string"
                },
                "remark": {
                    "description": "角色备注",
                    "type": "string"
                }
            }
        },
        "request.SystemUserAddReq": {
            "type": "object",
            "required": [
                "email",
                "nickname",
                "password",
                "role_id",
                "username"
            ],
            "properties": {
                "email": {
                    "description": "用户邮箱",
                    "type": "string"
                },
                "nickname": {
                    "description": "用户昵称",
                    "type": "string"
                },
                "password": {
                    "description": "密码",
                    "type": "string"
                },
                "remark": {
                    "description": "用户备注",
                    "type": "string"
                },
                "role_id": {
                    "description": "角色ID",
                    "type": "string"
                },
                "status": {
                    "description": "用户状态 [1: 启用, 2: 禁用]",
                    "allOf": [
                        {
                            "$ref": "#/definitions/constant.YesOrNo"
                        }
                    ]
                },
                "username": {
                    "description": "用户名",
                    "type": "string"
                }
            }
        },
        "request.SystemUserEditPasswordReq": {
            "type": "object",
            "required": [
                "confirm_password",
                "new_password",
                "pre_password"
            ],
            "properties": {
                "confirm_password": {
                    "description": "确认密码",
                    "type": "string"
                },
                "new_password": {
                    "description": "新密码",
                    "type": "string"
                },
                "pre_password": {
                    "description": "旧密码",
                    "type": "string"
                }
            }
        },
        "request.SystemUserUpdateReq": {
            "type": "object",
            "properties": {
                "email": {
                    "description": "用户邮箱",
                    "type": "string"
                },
                "nickname": {
                    "description": "用户昵称",
                    "type": "string"
                },
                "remark": {
                    "description": "用户备注",
                    "type": "string"
                },
                "role_id": {
                    "description": "角色ID",
                    "type": "string"
                },
                "username": {
                    "description": "用户名",
                    "type": "string"
                }
            }
        },
        "response.CaptchaResponse": {
            "type": "object",
            "properties": {
                "id": {
                    "description": "验证码id",
                    "type": "string",
                    "example": "1234567890"
                },
                "length": {
                    "description": "验证码长度",
                    "type": "integer",
                    "example": 4
                },
                "pictures": {
                    "description": "验证码图片",
                    "type": "string",
                    "example": "base64"
                }
            }
        },
        "response.Options": {
            "type": "object",
            "properties": {
                "children": {
                    "description": "子级选项",
                    "type": "array",
                    "items": {
                        "$ref": "#/definitions/response.Options"
                    }
                },
                "label": {
                    "description": "名称",
                    "type": "string"
                },
                "value": {
                    "description": "值",
                    "type": "string"
                }
            }
        },
        "response.SystemInfoResponse": {
            "type": "object",
            "properties": {
                "nickname": {
                    "description": "用户昵称",
                    "type": "string"
                },
                "role_name": {
                    "description": "角色名称",
                    "type": "string"
                },
                "token": {
                    "description": "token",
                    "type": "string"
                },
                "username": {
                    "description": "用户名",
                    "type": "string"
                }
            }
        },
        "response.SystemOnlineUserListResp": {
            "type": "object",
            "properties": {
                "items": {
                    "description": "在线用户列表",
                    "type": "array",
                    "items": {
                        "$ref": "#/definitions/response.SystemOnlineUserResp"
                    }
                },
                "page": {
                    "description": "页码",
                    "type": "integer"
                },
                "page_size": {
                    "description": "每页条数",
                    "type": "integer"
                },
                "total": {
                    "description": "总条数",
                    "type": "integer"
                }
            }
        },
        "response.SystemOnlineUserResp": {
            "type": "object",
            "properties": {
                "access_ip": {
                    "description": "访问IP",
                    "type": "string"
                },
                "browser_engine_name": {
                    "description": "浏览器引擎名称",
                    "type": "string"
                },
                "browser_engine_version": {
                    "description": "浏览器引擎版本",
                    "type": "string"
                },
                "browser_name": {
                    "description": "浏览器名称",
                    "type": "string"
                },
                "browser_version": {
                    "description": "浏览器版本",
                    "type": "string"
                },
                "id": {
                    "description": "ID",
                    "type": "string"
                },
                "last_operation_time": {
                    "description": "最后操作时间",
                    "type": "integer"
                },
                "nickname": {
                    "description": "用户昵称",
                    "type": "string"
                },
                "operation_type": {
                    "description": "操作类型",
                    "allOf": [
                        {
                            "$ref": "#/definitions/common.OperationType"
                        }
                    ]
                },
                "os": {
                    "description": "操作系统",
                    "type": "string"
                },
                "platform": {
                    "description": "操作平台",
                    "type": "string"
                },
                "username": {
                    "description": "用户名",
                    "type": "string"
                }
            }
        },
        "response.SystemRoleListResp": {
            "type": "object",
            "properties": {
                "items": {
                    "description": "角色列表",
                    "type": "array",
                    "items": {
                        "$ref": "#/definitions/response.SystemRoleResp"
                    }
                },
                "page": {
                    "description": "页码",
                    "type": "integer"
                },
                "page_size": {
                    "description": "每页条数",
                    "type": "integer"
                },
                "total": {
                    "description": "总条数",
                    "type": "integer"
                }
            }
        },
        "response.SystemRoleResp": {
            "type": "object",
            "properties": {
                "id": {
                    "description": "角色ID",
                    "type": "string"
                },
                "name": {
                    "description": "角色名称",
                    "type": "string"
                },
                "remark": {
                    "description": "角色备注",
                    "type": "string"
                },
                "status": {
                    "description": "角色状态 [1: 启用, 2: 禁用]",
                    "allOf": [
                        {
                            "$ref": "#/definitions/constant.YesOrNo"
                        }
                    ]
                }
            }
        },
        "response.SystemUserListResp": {
            "type": "object",
            "properties": {
                "items": {
                    "description": "用户列表",
                    "type": "array",
                    "items": {
                        "$ref": "#/definitions/response.SystemUserResp"
                    }
                },
                "page": {
                    "description": "页码",
                    "type": "integer"
                },
                "page_size": {
                    "description": "每页条数",
                    "type": "integer"
                },
                "total": {
                    "description": "总条数",
                    "type": "integer"
                }
            }
        },
        "response.SystemUserResp": {
            "type": "object",
            "properties": {
                "email": {
                    "description": "用户邮箱",
                    "type": "string"
                },
                "id": {
                    "description": "用户ID",
                    "type": "string"
                },
                "last_operation_time": {
                    "description": "最后操作时间",
                    "type": "integer"
                },
                "last_password_change": {
                    "description": "最后密码修改时间",
                    "type": "integer"
                },
                "nickname": {
                    "description": "用户昵称",
                    "type": "string"
                },
                "operation_type": {
                    "description": "操作类型",
                    "allOf": [
                        {
                            "$ref": "#/definitions/common.OperationType"
                        }
                    ]
                },
                "remark": {
                    "description": "用户备注",
                    "type": "string"
                },
                "role_id": {
                    "description": "角色ID",
                    "type": "string"
                },
                "role_name": {
                    "description": "角色名称",
                    "type": "string"
                },
                "status": {
                    "description": "用户状态 [1: 启用, 2: 禁用]",
                    "allOf": [
                        {
                            "$ref": "#/definitions/constant.YesOrNo"
                        }
                    ]
                },
                "username": {
                    "description": "用户名",
                    "type": "string"
                }
            }
        }
    },
    "securityDefinitions": {
        "ApiKeyAuth": {
            "description": "token认证",
            "type": "apiKey",
            "name": "Authorization",
            "in": "header"
        }
    }
}